[
  {
    "polygon": [
      {
        "x": -28,
        "y": -12
      },
      {
        "x": -8,
        "y": -8
      },
      {
        "x": 6.44389438943892,
        "y": 5.27227722772275
      },
      {
        "x": 45,
        "y": 37
      },
      {
        "x": 45,
        "y": 131
      },
      {
        "x": 92,
        "y": 132
      },
      {
        "x": 140,
        "y": 84
      },
      {
        "x": 172,
        "y": 84
      },
      {
        "x": 172,
        "y": 68
      },
      {
        "x": 220,
        "y": 68
      },
      {
        "x": 220,
        "y": 84
      },
      {
        "x": 204,
        "y": 100
      },
      {
        "x": 204,
        "y": 116
      },
      {
        "x": 156,
        "y": 116
      },
      {
        "x": 108,
        "y": 164
      },
      {
        "x": 45,
        "y": 164
      },
      {
        "x": 45,
        "y": 181
      },
      {
        "x": -4,
        "y": 228
      },
      {
        "x": -4,
        "y": 320
      },
      {
        "x": -132,
        "y": 452
      },
      {
        "x": -132,
        "y": 548
      },
      {
        "x": -84,
        "y": 596
      },
      {
        "x": -20,
        "y": 596
      },
      {
        "x": -20,
        "y": 580
      },
      {
        "x": -4,
        "y": 580
      },
      {
        "x": -4,
        "y": 628
      },
      {
        "x": -100,
        "y": 628
      },
      {
        "x": -164,
        "y": 564
      },
      {
        "x": -164,
        "y": 436
      },
      {
        "x": -228,
        "y": 372
      },
      {
        "x": -276,
        "y": 372
      },
      {
        "x": -324,
        "y": 324
      },
      {
        "x": -380,
        "y": 324
      },
      {
        "x": -380,
        "y": 292
      },
      {
        "x": -308,
        "y": 292
      },
      {
        "x": -260,
        "y": 340
      },
      {
        "x": -212,
        "y": 340
      },
      {
        "x": -148,
        "y": 404
      },
      {
        "x": -132,
        "y": 404
      },
      {
        "x": -36,
        "y": 308
      },
      {
        "x": -36,
        "y": 212
      },
      {
        "x": 12,
        "y": 164
      },
      {
        "x": 12,
        "y": 52
      },
      {
        "x": -20,
        "y": 20
      },
      {
        "x": -52,
        "y": 20
      },
      {
        "x": -52,
        "y": -12
      }
    ],
    "x": 468,
    "y": 252
  },
  {
    "height": 32,
    "name": "toPoland",
    "width": 0,
    "x": 88,
    "y": 544
  },
  {
    "height": 0,
    "name": "toBelarusHome",
    "width": 16,
    "x": 448,
    "y": 832
  },
  {
    "height": 0,
    "name": "toBelarusWork",
    "width": 16,
    "x": 656,
    "y": 320
  },
  {
    "height": 0,
    "name": "toBelarusCollage",
    "width": 16,
    "x": 416,
    "y": 240
  }
]